LICENSE
README.md
setup.cfg
setup.py
algobacktest/Backtest.py
algobacktest.egg-info/PKG-INFO
algobacktest.egg-info/SOURCES.txt
algobacktest.egg-info/dependency_links.txt
algobacktest.egg-info/requires.txt
algobacktest.egg-info/top_level.txt
test/test_Backtest.py