Metadata-Version: 2.1
Name: algobacktest
Version: 0.0.2
Summary: Testing installation of Package
Home-page: https://github.com/algobacktest/
Author: Baris Arat
Author-email: hello@baristradingtech.com
License: MIT
Keywords: pypi,algobacktest
Classifier: Intended Audience :: Developers
Classifier: Topic :: Software Development :: Documentation
Classifier: License :: OSI Approved :: MIT License
Classifier: Programming Language :: Python :: 3.9
License-File: LICENSE
